fpd/__init__.py
fpd/dpc_explorer_class.py
fpd/fft_tools.py
fpd/fpd_file.py
fpd/fpd_io.py
fpd/fpd_processing.py
fpd/gwy.py
fpd/mag_tools.py
fpd/perceptually_uniform_cmap.npy
fpd/ransac_tools.py
fpd/segmented_dpc_class.py
fpd/synthetic_data.py
fpd/tem_tools.py
fpd/utils.py
fpd-0.1.10.dist-info/METADATA
fpd-0.1.10.dist-info/RECORD
fpd-0.1.10.dist-info/WHEEL
fpd-0.1.10.dist-info/top_level.txt
fpd-0.1.10.dist-info/zip-safe
