Metadata-Version: 2.1
Name: fpd
Version: 0.1.10
Summary: FPD: Fast pixelated detector data storage, analysis and visualisation.
Home-page: http://gitlab.com/fpdpy/fpd
Author: Gary Paterson
Author-email: gary.paterson@glasgow.ac.uk
License: GPL v3
Keywords: microscopy,STEM,TEM,fast pixelated detector,fpd,data storage,EMD,hdf5,data analysis,differential phase contrast,DPC,segmented DPC,pixelated DPC,virtual detector,lattice analyis,strain analysis
Platform: UNKNOWN
Classifier: Development Status :: 5 - Production/Stable
Classifier: License :: OSI Approved :: GNU General Public License v3 (GPLv3)
Classifier: Programming Language :: Python :: 2.7
Classifier: Programming Language :: Python :: 3
Classifier: Topic :: Scientific/Engineering :: Physics
Requires-Dist: numpy
Requires-Dist: scipy
Requires-Dist: scikit-image
Requires-Dist: matplotlib
Requires-Dist: h5py
Requires-Dist: tqdm
Requires-Dist: hyperspy
